{
  "limit": "60",
  "page": "1",
  "toys": [
    {
      "id": 551216,
      "id_list": "551216",
      "sku": "david",
      "price": "105.00",
      "size": 1,
      "firmness": 9,
      "cumtube": 13,
      "suction_cup": 22,
      "color_theme": null,
      "created": "2021-09-21T21:05:33.600Z",
      "weight": "1.44",
      "is_flop": false,
      "external_flop_reason": null,
      "color_display": "Rogue",
      "original_price": "105.00",
      "images": [
        {
          "id": 733161,
          "inventoryToyId": 551216,
          "created": "2021-09-29T21:24:51.433Z",
          "sortOrder": 10,
          "imageUrlFull": "https://da6npmvqm28oa.cloudfront.net/inventory-toy-services/411f6286-dee2-46ca-ad10-203fb1c1cae4.jpg",
          "imageUrl450": "https://da6npmvqm28oa.cloudfront.net/inventory-toy-services/af0b775e-4b00-44bd-80f1-a0c8d1383f51.jpg",
          "imageUrl240": "https://da6npmvqm28oa.cloudfront.net/inventory-toy-services/078eb675-1cfb-4bdd-8971-fafcd57d66dc.jpg",
          "imageUrl150": "https://da6npmvqm28oa.cloudfront.net/inventory-toy-services/e2bd3abf-51f9-4b40-a09e-e28a9234f23c.jpg",
          "imageUrl1200": "https://da6npmvqm28oa.cloudfront.net/inventory-toy-services/231a3d6a-925b-430e-b8b3-8051517c0f5d.jpg",
          "isFlopPhoto": false
        }
      ]
    },
    {
      "id": 555107,
      "id_list": "555107",
      "sku": "echo",
      "price": "125.00",
      "size": 1,
      "firmness": 12,
      "cumtube": 13,
      "suction_cup": 22,
      "color_theme": null,
      "created": "2021-09-27T22:17:11.411Z",
      "weight": "1.64",
      "is_flop": false,
      "external_flop_reason": "",
      "color_display": "Rogue",
      "original_price": "125.00",
      "images": [
        {
          "id": 731042,
          "inventoryToyId": 555107,
          "created": "2021-09-27T23:47:09.685Z",
          "sortOrder": 10,
          "imageUrlFull": "https://da6npmvqm28oa.cloudfront.net/inventory-toy-services/0e4b4a60-9f96-40d8-ba11-7024e2fbfdd6.jpg",
          "imageUrl450": "https://da6npmvqm28oa.cloudfront.net/inventory-toy-services/b51062e2-37fd-4316-90e3-87a511319865.jpg",
          "imageUrl240": "https://da6npmvqm28oa.cloudfront.net/inventory-toy-services/495ba60e-c66a-4d57-9f46-b1dac2f570cc.jpg",
          "imageUrl150": "https://da6npmvqm28oa.cloudfront.net/inventory-toy-services/cfb829e7-ba52-4673-a98f-3ee8ff0b0546.jpg",
          "imageUrl1200": "https://da6npmvqm28oa.cloudfront.net/inventory-toy-services/d93db213-5595-47e9-8586-2acad1851e7d.jpg",
          "isFlopPhoto": false
        }
      ]
    },
    {
      "id": 552145,
      "id_list": "552145",
      "sku": "bumblehooves",
      "price": "135.00",
      "size": 2,
      "firmness": 4,
      "cumtube": 13,
      "suction_cup": 22,
      "color_theme": null,
      "created": "2021-09-22T22:34:17.824Z",
      "weight": "2.89",
      "is_flop": false,
      "external_flop_reason": null,
      "color_display": "Rogue",
      "original_price": "135.00",
      "images": [
        {
          "id": 731069,
          "inventoryToyId": 552145,
          "created": "2021-09-28T00:18:53.766Z",
          "sortOrder": 10,
          "imageUrlFull": "https://da6npmvqm28oa.cloudfront.net/inventory-toy-services/a70f7d7e-4f08-4fb3-8b26-d9abd157d1e7.jpg",
          "imageUrl450": "https://da6npmvqm28oa.cloudfront.net/inventory-toy-services/33fc353c-000b-48b1-bf77-6bc247ebf83d.jpg",
          "imageUrl240": "https://da6npmvqm28oa.cloudfront.net/inventory-toy-services/5018e62f-de8c-454d-940f-e736ddf7683a.jpg",
          "imageUrl150": "https://da6npmvqm28oa.cloudfront.net/inventory-toy-services/5f94f951-623b-43c5-96ad-369a2cefd517.jpg",
          "imageUrl1200": "https://da6npmvqm28oa.cloudfront.net/inventory-toy-services/40ecaf3e-3a86-4f25-b6d0-0d7e8cecfd3d.jpg",
          "isFlopPhoto": false
        }
      ]
    },
    {
      "id": 556365,
      "id_list": "556385, 556365",
      "sku": "bruiser",
      "price": "135.00",
      "size": 2,
      "firmness": 4,
      "cumtube": 13,
      "suction_cup": 22,
      "color_theme": 92,
      "created": "2021-09-29T22:06:38.149Z",
      "weight": "2.34",
      "is_flop": false,
      "external_flop_reason": null,
      "color_display": "",
      "original_price": "135.00",
      "images": [
        {
          "id": 733264,
          "inventoryToyId": 556365,
          "created": "2021-09-29T22:06:38.178Z",
          "sortOrder": 0,
          "imageUrlFull": "https://da6npmvqm28oa.cloudfront.net/inventory-toy-services/347d6512-10cb-430e-9480-7f32b6e8a569.jpg",
          "imageUrl450": "https://da6npmvqm28oa.cloudfront.net/inventory-toy-services/b839d124-266d-4a81-b2c7-2f9c5255f2bd.jpg",
          "imageUrl240": "https://da6npmvqm28oa.cloudfront.net/inventory-toy-services/47361661-e413-466e-af38-11bd26e81267.jpg",
          "imageUrl150": "https://da6npmvqm28oa.cloudfront.net/inventory-toy-services/7580e02a-b0aa-4ae6-a5b9-cbbd320f3066.jpg",
          "imageUrl1200": "https://da6npmvqm28oa.cloudfront.net/inventory-toy-services/76b9f078-ffe3-4682-ae61-ce8478f3dfd3.jpg",
          "isFlopPhoto": false
        }
      ],
      "colorTheme": {
        "id": 92,
        "name": "Bruiser's Natural",
        "description": "A light blue highlight over a maroon shaft and purple base.",
        "bodyOptionId": 76,
        "baseOptionId": 37,
        "priceModifier": "0.00",
        "singleProduct": true,
        "specification": "{\"body\":{\"type\":\"highlight\",\"color1\":\"a75f77\",\"colorStops\":[],\"color2\":\"aee6ff\"},\"base\":{\"type\":\"split\",\"color1\":\"a78ec5\"}}",
        "isSurpriseMe": false,
        "globalPreviewOverrideImage": null,
        "swatchImageId": 4356,
        "sort_order": 0,
        "startDate": "2020-09-03T23:19:16.113Z",
        "endDate": null
      }
    },
    {
      "id": 550426,
      "id_list": "550426",
      "sku": "tyson",
      "price": "145.00",
      "size": 2,
      "firmness": 4,
      "cumtube": 13,
      "suction_cup": 23,
      "color_theme": null,
      "created": "2021-09-21T04:31:42.625Z",
      "weight": "2.17",
      "is_flop": false,
      "external_flop_reason": null,
      "color_display": "Rogue",
      "original_price": "135.00",
      "images": [
        {
          "id": 731162,
          "inventoryToyId": 550426,
          "created": "2021-09-28T03:16:04.979Z",
          "sortOrder": 10,
          "imageUrlFull": "https://da6npmvqm28oa.cloudfront.net/inventory-toy-services/ccd32957-030b-45e2-a894-b9394f607452.jpg",
          "imageUrl450": "https://da6npmvqm28oa.cloudfront.net/inventory-toy-services/00bff7cd-c2a2-4667-8580-d54e08a82bb8.jpg",
          "imageUrl240": "https://da6npmvqm28oa.cloudfront.net/inventory-toy-services/0ff1f2d9-88ad-44b0-8a50-cc8660592e2a.jpg",
          "imageUrl150": "https://da6npmvqm28oa.cloudfront.net/inventory-toy-services/2b6c9a51-5919-472a-917e-e31e6c3362f7.jpg",
          "imageUrl1200": "https://da6npmvqm28oa.cloudfront.net/inventory-toy-services/cdce753a-8c07-4c78-83b9-3ad3a5406f6c.jpg",
          "isFlopPhoto": false
        }
      ]
    },
    {
      "id": 555291,
      "id_list": "555291",
      "sku": "vector",
      "price": "145.00",
      "size": 2,
      "firmness": 9,
      "cumtube": 13,
      "suction_cup": 23,
      "color_theme": null,
      "created": "2021-09-28T14:31:52.617Z",
      "weight": "3.05",
      "is_flop": false,
      "external_flop_reason": "",
      "color_display": "Rogue",
      "original_price": "145.00",
      "images": [
        {
          "id": 733159,
          "inventoryToyId": 555291,
          "created": "2021-09-29T21:23:25.155Z",
          "sortOrder": 10,
          "imageUrlFull": "https://da6npmvqm28oa.cloudfront.net/inventory-toy-services/85ac03ef-3389-4fc1-96a1-a3ca7687de71.jpg",
          "imageUrl450": "https://da6npmvqm28oa.cloudfront.net/inventory-toy-services/a512c9f2-6e02-43d7-a65a-1fd714d1b9f5.jpg",
          "imageUrl240": "https://da6npmvqm28oa.cloudfront.net/inventory-toy-services/9345851a-d126-42e3-9781-08e1d5ed5420.jpg",
          "imageUrl150": "https://da6npmvqm28oa.cloudfront.net/inventory-toy-services/9aeee6f2-dff8-4a0f-8528-2fc00099105c.jpg",
          "imageUrl1200": "https://da6npmvqm28oa.cloudfront.net/inventory-toy-services/e3222e8d-4fca-47b1-9f18-3ebb04e39a1c.jpg",
          "isFlopPhoto": false
        }
      ]
    },
    {
      "id": 556165,
      "id_list": "556165",
      "sku": "vector",
      "price": "145.00",
      "size": 2,
      "firmness": 9,
      "cumtube": 13,
      "suction_cup": 23,
      "color_theme": 905,
      "created": "2021-09-29T15:45:31.120Z",
      "weight": "3.05",
      "is_flop": false,
      "external_flop_reason": null,
      "color_display": "",
      "original_price": "145.00",
      "images": [
        {
          "id": 732689,
          "inventoryToyId": 556165,
          "created": "2021-09-29T15:45:31.147Z",
          "sortOrder": 0,
          "imageUrlFull": "https://da6npmvqm28oa.cloudfront.net/inventory-toy-services/1c8923f5-900c-44c0-8bde-266ac3afbb62.jpg",
          "imageUrl450": "https://da6npmvqm28oa.cloudfront.net/inventory-toy-services/7cb27f74-fdd6-47b4-8184-4cb94729fc28.jpg",
          "imageUrl240": "https://da6npmvqm28oa.cloudfront.net/inventory-toy-services/b9fbfcf1-9f82-4a08-ab27-71541ac92838.jpg",
          "imageUrl150": "https://da6npmvqm28oa.cloudfront.net/inventory-toy-services/0002af03-c65f-4cb1-82a3-2139c443174a.jpg",
          "imageUrl1200": "https://da6npmvqm28oa.cloudfront.net/inventory-toy-services/f1ccb4e4-d0cd-4a40-81ea-04f87262a38d.jpg",
          "isFlopPhoto": false
        }
      ],
      "colorTheme": {
        "id": 905,
        "name": "Vector's Natural",
        "description": "A defiant, UV Reactive Cyber Punk marble of a Loud Neon Magenta, A Brilliant Neon White, and a Bright Neon Blue",
        "bodyOptionId": 39,
        "baseOptionId": 35,
        "priceModifier": "0.00",
        "singleProduct": true,
        "specification": "{\"body\":{\"type\":\"marble-custom\",\"color1\":\"FFFFFF\",\"colorStops\":[{\"position\":0.412,\"hexCode\":\"fb38cf\"},{\"position\":0.657,\"hexCode\":\"00ccff\"},{\"position\":0.562,\"hexCode\":\"ffffff\"},{\"position\":0.977,\"hexCode\":\"00ccff\"},{\"position\":0.865,\"hexCode\":\"ffffff\"},{\"position\":0.769,\"hexCode\":\"fb38cf\"},{\"position\":0.231,\"hexCode\":\"00ccff\"},{\"position\":0.135,\"hexCode\":\"ffffff\"},{\"position\":0.057,\"hexCode\":\"fb38cf\"}]}}",
        "isSurpriseMe": false,
        "globalPreviewOverrideImage": null,
        "swatchImageId": 10471,
        "sort_order": 6240,
        "startDate": "2021-06-24T07:00:00.000Z",
        "endDate": null
      }
    },
    {
      "id": 556937,
      "id_list": "556937",
      "sku": "vector",
      "price": "165.00",
      "size": 2,
      "firmness": 4,
      "cumtube": 13,
      "suction_cup": 23,
      "color_theme": 906,
      "created": "2021-09-30T18:24:20.316Z",
      "weight": "3.05",
      "is_flop": false,
      "external_flop_reason": null,
      "color_display": "",
      "original_price": "155.00",
      "images": [
        {
          "id": 734012,
          "inventoryToyId": 556937,
          "created": "2021-09-30T18:24:20.353Z",
          "sortOrder": 0,
          "imageUrlFull": "https://da6npmvqm28oa.cloudfront.net/inventory-toy-services/f4ee4cc3-936a-4f45-b291-e753cb24d948.jpg",
          "imageUrl450": "https://da6npmvqm28oa.cloudfront.net/inventory-toy-services/8ae6ea16-3afd-4ac4-9b9c-e020af15853a.jpg",
          "imageUrl240": "https://da6npmvqm28oa.cloudfront.net/inventory-toy-services/6b9e2948-7d4f-49b8-9a26-188e25ad848a.jpg",
          "imageUrl150": "https://da6npmvqm28oa.cloudfront.net/inventory-toy-services/62e883a9-02e4-4549-943f-fef0beb35b91.jpg",
          "imageUrl1200": "https://da6npmvqm28oa.cloudfront.net/inventory-toy-services/61e6a344-69f7-419d-b783-ad88ee6e88ce.jpg",
          "isFlopPhoto": false
        }
      ],
      "colorTheme": {
        "id": 906,
        "name": "Vector's Signature",
        "description": "A subtle robotic fade transitioning from a Bright Metallic Cyan, to Dark Blue, to Purple, and finally to an industrial, machine-like Black",
        "bodyOptionId": 36,
        "baseOptionId": 35,
        "priceModifier": "20.00",
        "singleProduct": true,
        "specification": "{\"body\":{\"type\":\"fade-custom\",\"color1\":\"FFFFFF\",\"colorStops\":[{\"position\":0.304,\"hexCode\":\"4c4748\"},{\"position\":0.642,\"hexCode\":\"4f9acf\"},{\"position\":0.862,\"hexCode\":\"9ef3ff\"},{\"position\":0.458,\"hexCode\":\"7876ab\"}]}}",
        "isSurpriseMe": false,
        "globalPreviewOverrideImage": null,
        "swatchImageId": 10472,
        "sort_order": 6250,
        "startDate": "2021-06-24T07:00:00.000Z",
        "endDate": null
      }
    },
    {
      "id": 557021,
      "id_list": "557021",
      "sku": "vector",
      "price": "165.00",
      "size": 2,
      "firmness": 4,
      "cumtube": 13,
      "suction_cup": 23,
      "color_theme": 906,
      "created": "2021-09-30T21:19:52.034Z",
      "weight": "3.05",
      "is_flop": false,
      "external_flop_reason": null,
      "color_display": "",
      "original_price": "165.00",
      "images": [
        {
          "id": 734249,
          "inventoryToyId": 557021,
          "created": "2021-09-30T21:19:52.069Z",
          "sortOrder": 0,
          "imageUrlFull": "https://da6npmvqm28oa.cloudfront.net/inventory-toy-services/f4ee4cc3-936a-4f45-b291-e753cb24d948.jpg",
          "imageUrl450": "https://da6npmvqm28oa.cloudfront.net/inventory-toy-services/8ae6ea16-3afd-4ac4-9b9c-e020af15853a.jpg",
          "imageUrl240": "https://da6npmvqm28oa.cloudfront.net/inventory-toy-services/6b9e2948-7d4f-49b8-9a26-188e25ad848a.jpg",
          "imageUrl150": "https://da6npmvqm28oa.cloudfront.net/inventory-toy-services/62e883a9-02e4-4549-943f-fef0beb35b91.jpg",
          "imageUrl1200": "https://da6npmvqm28oa.cloudfront.net/inventory-toy-services/61e6a344-69f7-419d-b783-ad88ee6e88ce.jpg",
          "isFlopPhoto": false
        }
      ],
      "colorTheme": {
        "id": 906,
        "name": "Vector's Signature",
        "description": "A subtle robotic fade transitioning from a Bright Metallic Cyan, to Dark Blue, to Purple, and finally to an industrial, machine-like Black",
        "bodyOptionId": 36,
        "baseOptionId": 35,
        "priceModifier": "20.00",
        "singleProduct": true,
        "specification": "{\"body\":{\"type\":\"fade-custom\",\"color1\":\"FFFFFF\",\"colorStops\":[{\"position\":0.304,\"hexCode\":\"4c4748\"},{\"position\":0.642,\"hexCode\":\"4f9acf\"},{\"position\":0.862,\"hexCode\":\"9ef3ff\"},{\"position\":0.458,\"hexCode\":\"7876ab\"}]}}",
        "isSurpriseMe": false,
        "globalPreviewOverrideImage": null,
        "swatchImageId": 10472,
        "sort_order": 6250,
        "startDate": "2021-06-24T07:00:00.000Z",
        "endDate": null
      }
    },
    {
      "id": 557118,
      "id_list": "557118",
      "sku": "habu",
      "price": "165.00",
      "size": 2,
      "firmness": 9,
      "cumtube": 13,
      "suction_cup": 23,
      "color_theme": 904,
      "created": "2021-10-01T14:33:55.984Z",
      "weight": "3.57",
      "is_flop": false,
      "external_flop_reason": null,
      "color_display": "",
      "original_price": "165.00",
      "images": [
        {
          "id": 734866,
          "inventoryToyId": 557118,
          "created": "2021-10-01T14:33:56.028Z",
          "sortOrder": 0,
          "imageUrlFull": "https://da6npmvqm28oa.cloudfront.net/inventory-toy-services/67d496cb-10ff-44a9-a5f2-b185cb941dc2.jpg",
          "imageUrl450": "https://da6npmvqm28oa.cloudfront.net/inventory-toy-services/a15bad4d-1260-4bf3-8519-32ae4562a1e3.jpg",
          "imageUrl240": "https://da6npmvqm28oa.cloudfront.net/inventory-toy-services/91585aae-7378-42d8-9fd6-7d18ebfdc236.jpg",
          "imageUrl150": "https://da6npmvqm28oa.cloudfront.net/inventory-toy-services/8e9c2603-114f-4ca8-92d3-b01320b1baac.jpg",
          "imageUrl1200": "https://da6npmvqm28oa.cloudfront.net/inventory-toy-services/0f28cd0b-02c8-4ada-babf-c234ff2da8ce.jpg",
          "isFlopPhoto": false
        }
      ],
      "colorTheme": {
        "id": 904,
        "name": "Habu's Signature",
        "description": "A metallic Cyan shaft that is more than meets the eye, with a glow surprise of Aqua, Blue, and Purple, and a marbled base of Silver and gold flecked Black. * Glow patterns may vary and glow colors cannot be customized",
        "bodyOptionId": 36,
        "baseOptionId": 40,
        "priceModifier": "20.00",
        "singleProduct": true,
        "specification": "{\"body\":{\"type\":\"fade-custom\",\"color1\":\"afffe1\",\"colorStops\":[{\"position\":0.131,\"hexCode\":\"adffe0\"},{\"position\":0.5,\"hexCode\":\"afffe1\"},{\"position\":0.819,\"hexCode\":\"aaffdf\"}]},\"base\":{\"type\":\"marble\",\"color1\":\"e1e1e1\",\"color2\":\"323229\",\"color1Metallic\":{\"hue\":\"FFED66\",\"intensity\":0.5,\"sparkleScarcity\":8}}}",
        "isSurpriseMe": false,
        "globalPreviewOverrideImage": null,
        "swatchImageId": 10534,
        "sort_order": 6230,
        "startDate": "2021-07-29T07:00:00.000Z",
        "endDate": null
      }
    }
  ]
}